<?xml version="1.0" encoding="UTF-8"?>
<objects serializationModel="Studio.02.02.00">
	<object class="EncodingSetting" id="{d30b8780-3a3d-4410-80ad-2cba076d9886}">
		<property name="encodingFormat">
			<value>3</value>
		</property>
		<property name="quality">
			<value>37</value>
		</property>
		<relationship name="platform">
			<destination>{3853e4c1-2c60-4c14-ba69-11f957b8f4f4}</destination>
		</relationship>
		<relationship name="encodable">
			<destination>{3853e4c1-2c60-4c14-ba69-11f957b8f4f4}</destination>
		</relationship>
	</object>
</objects>
